CHANGES.txt
COPYING.txt
MANIFEST.in
README.rst
README.txt
development.ini
runtests.py
setup.cfg
setup.py
kotti_events/__init__.py
kotti_events/resources.py
kotti_events/util.py
kotti_events/views.py
kotti_events.egg-info/PKG-INFO
kotti_events.egg-info/SOURCES.txt
kotti_events.egg-info/dependency_links.txt
kotti_events.egg-info/entry_points.txt
kotti_events.egg-info/not-zip-safe
kotti_events.egg-info/requires.txt
kotti_events.egg-info/top_level.txt
kotti_events/locale/de_DE/LC_MESSAGES/kotti_events.mo
kotti_events/static/style.css
kotti_events/templates/event-view.pt
kotti_events/templates/eventfolder-view.pt
kotti_events/templates/eventpicture-view.pt
kotti_events/tests/browser.txt