Metadata-Version: 1.1
Name: kotti-events
Version: 0.1.0b3
Summary: Event collection for Kotti sites
Home-page: http://pypi.python.org/pypi/kotti_events
Author: Christian Neumann and contributors
Author-email: christian@datenkarussell.de
License: BSD License
Keywords: kotti contact form
Platform: UNKNOWN
Classifier: Development Status :: 4 - Beta
Classifier: Programming Language :: Python
Classifier: Framework :: Pylons
Classifier: Topic :: Internet :: WWW/HTTP
Classifier: Topic :: Internet :: WWW/HTTP :: Dynamic Content
Classifier: Topic :: Internet :: WWW/HTTP :: WSGI :: Application
Classifier: License :: OSI Approved :: BSD License
